corsort/__init__.py
corsort/chain_and_y.py
corsort/corsort.py
corsort/corsort_borda.py
corsort/corsort_chain_decomposition_merge_v.py
corsort/corsort_chain_decomposition_merge_x.py
corsort/corsort_delegate.py
corsort/corsort_gain.py
corsort/corsort_gain_lexi.py
corsort/distance_to_sorted_array.py
corsort/entropy_bound.py
corsort/jit_scorers.py
corsort/jit_sorts.py
corsort/merge.py
corsort/montecarlo.py
corsort/multi_merge.py
corsort/partition.py
corsort/presets.py
corsort/print_order_as_letters.py
corsort/scorers.py
corsort/sort.py
corsort/sort_asort_quickselect.py
corsort/sort_baiesort.py
corsort/sort_binary_insertion.py
corsort/sort_ford_johnson.py
corsort/sort_largest_interval.py
corsort/sort_merge_bottom_up.py
corsort/sort_merge_top_down.py
corsort/sort_multizip.py
corsort/sort_quick.py
corsort/sort_shell.py
corsort/split_pointer_lists.py
corsort/transitive_reduction.py
corsort/util_chains.py
corsort/util_latex.py
corsort/wrap_full_jit.py
corsort/wrap_sort_scorer.py
corsort-0.1.4.dist-info/AUTHORS.rst
corsort-0.1.4.dist-info/LICENSE
corsort-0.1.4.dist-info/METADATA
corsort-0.1.4.dist-info/WHEEL
corsort-0.1.4.dist-info/RECORD
