Metadata-Version: 2.3
Name: corsort
Version: 0.1.4
Summary: Comparison-Oriented Sort.
License: GNU General Public License v3
Author: Emma Caizergues
Author-email: emma.caizergues@gmail.com
Requires-Python: >=3.10
Classifier: License :: Other/Proprietary License
Classifier: Programming Language :: Python :: 3
Classifier: Programming Language :: Python :: 3.10
Classifier: Programming Language :: Python :: 3.11
Classifier: Programming Language :: Python :: 3.12
Classifier: Programming Language :: Python :: 3.13
Requires-Dist: multiprocess (>=0.70.15,<0.71.0)
Requires-Dist: networkx (>=3.2.1,<4.0.0)
Requires-Dist: numba (>=0.61.0,<0.62.0)
Requires-Dist: numpy (<2.0.0)
Requires-Dist: scipy (>=1.11,<2.0)
Requires-Dist: svvamp (>=0.10.0,<0.11.0)
Requires-Dist: tqdm (>=4.66.1,<5.0.0)
